offline_rl_ope/Dataset.py
offline_rl_ope/RuntimeChecks.py
offline_rl_ope/__init__.py
offline_rl_ope/_version.py
offline_rl_ope/types.py
offline_rl_ope/LowerBounds/Bootstrap.py
offline_rl_ope/LowerBounds/HCOPE.py
offline_rl_ope/LowerBounds/__init__.py
offline_rl_ope/Metrics/EffectiveSampleSize.py
offline_rl_ope/Metrics/MetricBase.py
offline_rl_ope/Metrics/ValidWeightsProp.py
offline_rl_ope/Metrics/__init__.py
offline_rl_ope/OPEEstimators/DirectMethod.py
offline_rl_ope/OPEEstimators/DoublyRobust.py
offline_rl_ope/OPEEstimators/EmpiricalMeanDenom.py
offline_rl_ope/OPEEstimators/IS.py
offline_rl_ope/OPEEstimators/WeightDenom.py
offline_rl_ope/OPEEstimators/__init__.py
offline_rl_ope/OPEEstimators/base.py
offline_rl_ope/OPEEstimators/utils.py
offline_rl_ope/PropensityModels/__init__.py
offline_rl_ope/PropensityModels/base.py
offline_rl_ope/PropensityModels/sklearn/Discrete.py
offline_rl_ope/PropensityModels/sklearn/__init__.py
offline_rl_ope/PropensityModels/torch/Trainer.py
offline_rl_ope/PropensityModels/torch/__init__.py
offline_rl_ope/PropensityModels/torch/models/Continuous.py
offline_rl_ope/PropensityModels/torch/models/Discrete.py
offline_rl_ope/PropensityModels/torch/models/__init__.py
offline_rl_ope/PropensityModels/torch/models/base.py
offline_rl_ope/api/__init__.py
offline_rl_ope/api/StandardEstimators/DR.py
offline_rl_ope/api/StandardEstimators/IS.py
offline_rl_ope/api/StandardEstimators/__init__.py
offline_rl_ope/api/d3rlpy/Misc.py
offline_rl_ope/api/d3rlpy/Policy.py
offline_rl_ope/api/d3rlpy/__init__.py
offline_rl_ope/api/d3rlpy/types.py
offline_rl_ope/api/d3rlpy/Callbacks/DM.py
offline_rl_ope/api/d3rlpy/Callbacks/IS.py
offline_rl_ope/api/d3rlpy/Callbacks/Misc.py
offline_rl_ope/api/d3rlpy/Callbacks/__init__.py
offline_rl_ope/api/d3rlpy/Callbacks/base.py
offline_rl_ope/api/d3rlpy/Scorers/IS.py
offline_rl_ope/api/d3rlpy/Scorers/Metrics.py
offline_rl_ope/api/d3rlpy/Scorers/Misc.py
offline_rl_ope/api/d3rlpy/Scorers/__init__.py
offline_rl_ope-7.0.0.dist-info/LICENSE.txt
offline_rl_ope-7.0.0.dist-info/METADATA
offline_rl_ope-7.0.0.dist-info/WHEEL
offline_rl_ope-7.0.0.dist-info/top_level.txt
offline_rl_ope-7.0.0.dist-info/RECORD
