Metadata-Version: 2.1
Name: offline_rl_ope
Version: 7.0.0
Home-page: 
Author: Joshua Spear
Author-email: josh.spear9@gmail.com
License: MIT
Requires-Python: >=3.10
License-File: LICENSE.txt
Requires-Dist: d3rlpy >=2.0.4
